pydantic_fhir/__init__.py
pydantic_fhir/r4.py
pydantic_fhir-0.0.1a18.dist-info/WHEEL
pydantic_fhir-0.0.1a18.dist-info/METADATA
pydantic_fhir-0.0.1a18.dist-info/RECORD
