Metadata-Version: 2.1
Name: pydantic-fhir
Version: 0.0.1a18
Summary: Generated FHIR model for Pydantic.
Home-page: https://github.com/skalarsystems/fhirzeug
License: Apache-2.0
Keywords: FHIR,pydantic
Author: Skalar Systems
Author-email: contact@skalarsystems.com
Requires-Python: >=3.8,<4.0
Classifier: Development Status :: 3 - Alpha
Classifier: Intended Audience :: Healthcare Industry
Classifier: License :: OSI Approved :: Apache Software License
Classifier: Programming Language :: Python :: 3
Classifier: Programming Language :: Python :: 3 :: Only
Classifier: Programming Language :: Python :: 3.8
Classifier: Programming Language :: Python :: 3.9
Classifier: Topic :: Software Development :: Code Generators
Classifier: Topic :: Software Development :: Libraries :: Python Modules
Requires-Dist: pydantic (>=1.5.1,<2.0.0)
Requires-Dist: stringcase (>=1.2.0,<2.0.0)
